stickydata/__init__.py
stickydata/stickydata.py
stickydata-0.1.dist-info/LICENSE
stickydata-0.1.dist-info/METADATA
stickydata-0.1.dist-info/WHEEL
stickydata-0.1.dist-info/top_level.txt
stickydata-0.1.dist-info/RECORD
