Metadata-Version: 2.1
Name: stickydata
Version: 0.1
Summary: package for correcting partitioning delays using deconvolution
Home-page: https://github.com/dpagonis/stickydata
Author: Demetrios Pagonis
Author-email: demetriospagonis@weber.edu
License-File: LICENSE
Requires-Dist: numpy
Requires-Dist: pandas
Requires-Dist: matplotlib
Requires-Dist: scipy
Requires-Dist: numba
